{
  "version": "v1",
  "blocklist": [],
  "data": [
    {
      "schema_version": "1.0.0",
      "id": "cherub_suite",
      "name": "Cherub Suite",
      "tagline": "Common pie menu helpers & Asset Library authoring utilities",
      "version": "0.3.4",
      "type": "add-on",
      "maintainer": "Luis Cherubini",
      "license": [
        "SPDX:GPL-3.0-or-later"
      ],
      "blender_version_min": "5.0.0",
      "website": "https://github.com/luischerub/Cherub-Suite",
      "permissions": {},
      "tags": [
        "Mesh",
        "Modeling",
        "Pipeline"
      ],
      "archive_url": "./cherub_suite.zip",
      "archive_size": 221935,
      "archive_hash": "sha256:db40fb6db6a36edc8d6d7c879f47ce7dc122372b932031e9d9fdf57b269342b0"
    }
  ]
}